colabrun/Client.py
colabrun/__init__.py
colabrun/common/Requests.py
colabrun/common/__init__.py
colabrun/common/config.py
colabrun/common/utils.py
colabrun/selenium/__init__.py
colabrun/selenium/elements.py
colabrun/selenium/locators.py
colabrun/selenium/page.py
colabrun-0.3.dist-info/METADATA
colabrun-0.3.dist-info/WHEEL
colabrun-0.3.dist-info/top_level.txt
colabrun-0.3.dist-info/RECORD
